LICENSE
MANIFEST.in
README.md
setup.py
examples/calculator.py
examples/calculator_op_prec.py
parstools/__init__.py
parstools/_enumerative_parsing.py
parstools/_ff.py
parstools/_grammars.py
parstools/_introspection.py
parstools/_lex.py
parstools/_re.py
parstools/_tla_grammars.py
parstools/_trees.py
parstools/_utils.py
parstools/_version.py
parstools/py.typed
parstools.egg-info/PKG-INFO
parstools.egg-info/SOURCES.txt
parstools.egg-info/dependency_links.txt
parstools.egg-info/top_level.txt
parstools/_lr/__init__.py
parstools/_lr/lr.py
parstools/_lr/lr_merging.py
parstools/_lr/lr_merging_opt.py
parstools/_lr/lrm_op_prec.py
parstools/_lr/parser.py
parstools/_lr/slr.py
parstools/_lr/utils.py
tests/ff_test.py
tests/grammars_test.py
tests/lexer_test.py
tests/lr_gen_test.py
tests/lr_merging_opt_test.py
tests/lr_parsing_test.py
tests/re_test.py