Metadata-Version: 2.1
Name: parstools
Version: 0.0.3
Summary: Parsing algorithms
Author: Ioannis Filippidis
Author-email: jfilippidis@gmail.com
License: Public Domain
Keywords: algorithms,grammar,lexer,lexing,LR(1),LR parser,parsers,parsing
Classifier: Development Status :: 2 - Pre-Alpha
Classifier: License :: Public Domain
Classifier: Operating System :: OS Independent
Classifier: Programming Language :: Python :: 3 :: Only
Requires-Python: >=3.11
License-File: LICENSE
